<annotation>
	<folder>images</folder>
	<filename>135.jpg</filename>
	<path>D:\0TFWin\images\135.jpg</path>
	<source>
		<database>Unknown</database>
	</source>
	<size>
		<width>346</width>
		<height>346</height>
		<depth>3</depth>
	</size>
	<segmented>0</segmented>
	<object>
		<name>boat</name>
		<pose>Unspecified</pose>
		<truncated>1</truncated>
		<difficult>0</difficult>
		<bndbox>
			<xmin>14</xmin>
			<ymin>162</ymin>
			<xmax>346</xmax>
			<ymax>294</ymax>
		</bndbox>
	</object>
	<object>
		<name>boat</name>
		<pose>Unspecified</pose>
		<truncated>0</truncated>
		<difficult>0</difficult>
		<bndbox>
			<xmin>5</xmin>
			<ymin>151</ymin>
			<xmax>49</xmax>
			<ymax>161</ymax>
		</bndbox>
	</object>
	<object>
		<name>boat</name>
		<pose>Unspecified</pose>
		<truncated>0</truncated>
		<difficult>0</difficult>
		<bndbox>
			<xmin>206</xmin>
			<ymin>150</ymin>
			<xmax>275</xmax>
			<ymax>163</ymax>
		</bndbox>
	</object>
	<object>
		<name>boat</name>
		<pose>Unspecified</pose>
		<truncated>0</truncated>
		<difficult>0</difficult>
		<bndbox>
			<xmin>286</xmin>
			<ymin>154</ymin>
			<xmax>335</xmax>
			<ymax>167</ymax>
		</bndbox>
	</object>
</annotation>
